DrawBridgeAPI/__init__.py
DrawBridgeAPI/api_server.py
DrawBridgeAPI/app.py
DrawBridgeAPI/backend/FLUX_falai.py
DrawBridgeAPI/backend/FLUX_replicate.py
DrawBridgeAPI/backend/SD_A1111_webui.py
DrawBridgeAPI/backend/SD_civitai_API.py
DrawBridgeAPI/backend/__init__.py
DrawBridgeAPI/backend/base.py
DrawBridgeAPI/backend/comfyui.py
DrawBridgeAPI/backend/liblibai.py
DrawBridgeAPI/backend/midjourney.py
DrawBridgeAPI/backend/novelai.py
DrawBridgeAPI/backend/seaart.py
DrawBridgeAPI/backend/tusiart.py
DrawBridgeAPI/backend/yunjie.py
DrawBridgeAPI/base_config.py
DrawBridgeAPI/comfyui_workflows/diaopony-hr.json
DrawBridgeAPI/comfyui_workflows/diaopony-hr_reflex.json
DrawBridgeAPI/comfyui_workflows/diaopony-tipo.json
DrawBridgeAPI/comfyui_workflows/diaopony-tipo_reflex.json
DrawBridgeAPI/comfyui_workflows/flux-dev.json
DrawBridgeAPI/comfyui_workflows/flux-dev_reflex.json
DrawBridgeAPI/comfyui_workflows/flux-schnell.json
DrawBridgeAPI/comfyui_workflows/flux-schnell_reflex.json
DrawBridgeAPI/comfyui_workflows/flux修手.json
DrawBridgeAPI/comfyui_workflows/flux修手_reflex.json
DrawBridgeAPI/comfyui_workflows/sd3.5_txt2img.json
DrawBridgeAPI/comfyui_workflows/sd3.5_txt2img_reflex.json
DrawBridgeAPI/comfyui_workflows/sdbase_img2img.json
DrawBridgeAPI/comfyui_workflows/sdbase_img2img_reflex.json
DrawBridgeAPI/comfyui_workflows/sdbase_txt2img.json
DrawBridgeAPI/comfyui_workflows/sdbase_txt2img_hr_fix.json
DrawBridgeAPI/comfyui_workflows/sdbase_txt2img_hr_fix_reflex.json
DrawBridgeAPI/comfyui_workflows/sdbase_txt2img_reflex.json
DrawBridgeAPI/comfyui_workflows/创意融字 工作流Jianan_创意融字海报.json
DrawBridgeAPI/config.yaml
DrawBridgeAPI/config_example.yaml
DrawBridgeAPI/dbapi.py
DrawBridgeAPI/locales/__init__.py
DrawBridgeAPI/locales/zh_CN/LC_MESSAGES/messages.mo
DrawBridgeAPI/locales/zh_CN/LC_MESSAGES/messages.po
DrawBridgeAPI/ui/__init__.py
DrawBridgeAPI/utils/__init__.py
DrawBridgeAPI/utils/custom_class.py
DrawBridgeAPI/utils/exceptions.py
DrawBridgeAPI/utils/llm_caption_requirements.txt
stable_diffusion_drawbridge_api-1.4.dist-info/METADATA
stable_diffusion_drawbridge_api-1.4.dist-info/WHEEL
stable_diffusion_drawbridge_api-1.4.dist-info/entry_points.txt
stable_diffusion_drawbridge_api-1.4.dist-info/licenses/LICENSE
stable_diffusion_drawbridge_api-1.4.dist-info/RECORD
