Metadata-Version: 2.1
Name: stable-diffusion-drawbridge-api
Version: 1.4
Summary: 使用标准A1111-SDWEBUI API来调用各种绘画后端的多功能负载均衡API
Author-Email: DiaoDaiaChan <diaodaiachan@qq.com>
Requires-Dist: aiohttp
Requires-Dist: aiofiles
Requires-Dist: Pillow>=10.4.0
Requires-Dist: civitai-py
Requires-Dist: civitai
Requires-Dist: colorama
Requires-Dist: fastapi
Requires-Dist: fal-client
Requires-Dist: httpx
Requires-Dist: piexif
Requires-Dist: pydantic
Requires-Dist: PyYAML
Requires-Dist: redis
Requires-Dist: replicate
Requires-Dist: tqdm
Requires-Dist: uvicorn
Requires-Dist: gradio
